async_q/__init__.py
async_q/__main__.py
async_q/async_q.py
async_q/async_worker.py
async_q/utils.py
async_q-0.2.dist-info/METADATA
async_q-0.2.dist-info/WHEEL
async_q-0.2.dist-info/license
async_q-0.2.dist-info/top_level.txt
async_q-0.2.dist-info/RECORD
