Metadata-Version: 2.1
Name: async-q
Version: 0.2
Summary: A simple worker task queue with async support 
Author-email: tumzied_ <abdur.rahman.tumzied.ewu@gmail.com>
Project-URL: Homepage, https://github.com/tz01x/async_q
Keywords: async,workers,queue,redis,distributed
Classifier: Programming Language :: Python :: 3
Classifier: License :: OSI Approved :: MIT License
Classifier: Operating System :: OS Independent
Requires-Python: >=3.8
License-File: license
Requires-Dist: redis ==5.0.0
Requires-Dist: msgpack
